datastore_viewer/__init__.py
datastore_viewer/__pycache__/__init__.cpython-37.pyc
datastore_viewer/infrastructure/__init__.py
datastore_viewer/infrastructure/__pycache__/__init__.cpython-37.pyc
datastore_viewer/presentation/__init__.py
datastore_viewer/presentation/__pycache__/__init__.cpython-37.pyc
datastore_viewer/presentation/template/datastore_viewer/asset-manifest.json
datastore_viewer/presentation/template/datastore_viewer/favicon.ico
datastore_viewer/presentation/template/datastore_viewer/index.html
datastore_viewer/presentation/template/datastore_viewer/logo192.png
datastore_viewer/presentation/template/datastore_viewer/logo512.png
datastore_viewer/presentation/template/datastore_viewer/manifest.json
datastore_viewer/presentation/template/datastore_viewer/precache-manifest.d13dc4d558e78a9aad33201fd07b7aa9.js
datastore_viewer/presentation/template/datastore_viewer/robots.txt
datastore_viewer/presentation/template/datastore_viewer/service-worker.js
datastore_viewer/presentation/template/datastore_viewer/static/css/main.a295f0a2.chunk.css
datastore_viewer/presentation/template/datastore_viewer/static/css/main.a295f0a2.chunk.css.map
datastore_viewer/presentation/template/datastore_viewer/static/js/2.8520b7fc.chunk.js
datastore_viewer/presentation/template/datastore_viewer/static/js/2.8520b7fc.chunk.js.LICENSE.txt
datastore_viewer/presentation/template/datastore_viewer/static/js/2.8520b7fc.chunk.js.map
datastore_viewer/presentation/template/datastore_viewer/static/js/main.6f94282b.chunk.js
datastore_viewer/presentation/template/datastore_viewer/static/js/main.6f94282b.chunk.js.map
datastore_viewer/presentation/template/datastore_viewer/static/js/runtime-main.84107d9c.js
datastore_viewer/presentation/template/datastore_viewer/static/js/runtime-main.84107d9c.js.map
datastore_viewer/presentation/ui/__init__.py
datastore_viewer/presentation/ui/html.py
datastore_viewer/presentation/ui/__pycache__/__init__.cpython-37.pyc
datastore_viewer-0.3.1.dist-info/LICENSE
datastore_viewer-0.3.1.dist-info/METADATA
datastore_viewer-0.3.1.dist-info/WHEEL
datastore_viewer-0.3.1.dist-info/top_level.txt
datastore_viewer-0.3.1.dist-info/RECORD
