Metadata-Version: 2.1
Name: datastore-viewer
Version: 0.3.1
Summary: Datastore Viewer for emulator
Home-page: https://github.com/gumo-py/datastore-viewer
Author: Gumo Project Team
Author-email: gumo-py@googlegroups.com
License: UNKNOWN
Platform: UNKNOWN
Classifier: Programming Language :: Python :: 3
Classifier: License :: OSI Approved :: MIT License
Classifier: Operating System :: OS Independent
Requires-Dist: google-cloud-datastore (>=1.7.0,>=1.8.0)
Requires-Dist: Flask (>=1.0.2)
Requires-Dist: flasgger (>=0.9.1)
